ml_scheduler/__init__.py
ml_scheduler/threads.py
ml_scheduler/exp/__init__.py
ml_scheduler/exp/exp.py
ml_scheduler/exp/func.py
ml_scheduler/exp/runner/__init__.py
ml_scheduler/exp/runner/base.py
ml_scheduler/exp/runner/csv.py
ml_scheduler/exp/runner/http.py
ml_scheduler/exp/runner/sqlite.py
ml_scheduler/pools/__init__.py
ml_scheduler/pools/base.py
ml_scheduler/pools/counter.py
ml_scheduler/pools/cuda.py
ml_scheduler/pools/disk.py
ml_scheduler-1.2.0.dist-info/METADATA
ml_scheduler-1.2.0.dist-info/WHEEL
ml_scheduler-1.2.0.dist-info/licenses/LICENSE
ml_scheduler-1.2.0.dist-info/RECORD
