Metadata-Version: 2.3
Name: ml_scheduler
Version: 1.2.0
Summary: A lightweight machine learning experiment scheduler that automates resource management (e.g., GPUs and models) and batch runs experiments with just a few lines of Python code.
Author-email: Yiwen Hu <1020030101@qq.com>
License-Expression: MIT
License-File: LICENSE
Keywords: artificial intelligence,async,large language model,machine learning,scheduler
Classifier: Development Status :: 4 - Beta
Classifier: Intended Audience :: Developers
Classifier: Intended Audience :: Education
Classifier: Intended Audience :: Science/Research
Classifier: Programming Language :: Python
Classifier: Topic :: Scientific/Engineering
Classifier: Topic :: Scientific/Engineering :: Artificial Intelligence
Classifier: Topic :: Software Development
Classifier: Topic :: Software Development :: Libraries
Classifier: Topic :: Software Development :: Libraries :: Python Modules
Requires-Python: >=3.8
Requires-Dist: coloredlogs
Requires-Dist: numpy>=2.0.0
Requires-Dist: nvitop
Requires-Dist: pandas
Requires-Dist: typing-extensions
Provides-Extra: dev
Requires-Dist: isort>=5.3; extra == 'dev'
Requires-Dist: pytest>=5.0; extra == 'dev'
